odoo/addons/mrp_lot_number_propagation/README.rst
odoo/addons/mrp_lot_number_propagation/__init__.py
odoo/addons/mrp_lot_number_propagation/__manifest__.py
odoo/addons/mrp_lot_number_propagation/i18n/es.po
odoo/addons/mrp_lot_number_propagation/i18n/it.po
odoo/addons/mrp_lot_number_propagation/i18n/mrp_lot_number_propagation.pot
odoo/addons/mrp_lot_number_propagation/i18n/nl.po
odoo/addons/mrp_lot_number_propagation/i18n/pt_BR.po
odoo/addons/mrp_lot_number_propagation/models/__init__.py
odoo/addons/mrp_lot_number_propagation/models/mrp_bom.py
odoo/addons/mrp_lot_number_propagation/models/mrp_bom_line.py
odoo/addons/mrp_lot_number_propagation/models/mrp_production.py
odoo/addons/mrp_lot_number_propagation/models/product_product.py
odoo/addons/mrp_lot_number_propagation/models/product_template.py
odoo/addons/mrp_lot_number_propagation/models/stock_move.py
odoo/addons/mrp_lot_number_propagation/readme/CONTRIBUTORS.md
odoo/addons/mrp_lot_number_propagation/readme/DESCRIPTION.md
odoo/addons/mrp_lot_number_propagation/readme/ROADMAP.md
odoo/addons/mrp_lot_number_propagation/security/ir.model.access.csv
odoo/addons/mrp_lot_number_propagation/static/description/icon.png
odoo/addons/mrp_lot_number_propagation/static/description/index.html
odoo/addons/mrp_lot_number_propagation/tests/__init__.py
odoo/addons/mrp_lot_number_propagation/tests/common.py
odoo/addons/mrp_lot_number_propagation/tests/test_mrp_bom.py
odoo/addons/mrp_lot_number_propagation/tests/test_mrp_production.py
odoo/addons/mrp_lot_number_propagation/views/mrp_bom.xml
odoo/addons/mrp_lot_number_propagation/views/mrp_production.xml
odoo/addons/mrp_lot_number_propagation/wizard/__init__.py
odoo/addons/mrp_lot_number_propagation/wizard/mrp_batch_produce.py
odoo/addons/mrp_lot_number_propagation/wizard/mrp_batch_produce.xml
odoo/addons/mrp_lot_number_propagation/wizard/mrp_batch_produce_propagate.py
odoo/addons/mrp_lot_number_propagation/wizard/mrp_batch_produce_propagate.xml
odoo_addon_mrp_lot_number_propagation-18.0.1.1.1.dist-info/METADATA
odoo_addon_mrp_lot_number_propagation-18.0.1.1.1.dist-info/WHEEL
odoo_addon_mrp_lot_number_propagation-18.0.1.1.1.dist-info/top_level.txt
odoo_addon_mrp_lot_number_propagation-18.0.1.1.1.dist-info/RECORD
